writerai_meta/__init__.py
writerai-4.0.1.dist-info/METADATA
writerai-4.0.1.dist-info/WHEEL
writerai-4.0.1.dist-info/RECORD
